setup.py
zk111.egg-info/PKG-INFO
zk111.egg-info/SOURCES.txt
zk111.egg-info/dependency_links.txt
zk111.egg-info/top_level.txt
zk_01/__init__.py
zk_01/add.py
zk_01/sub.py