Metadata-Version: 2.1
Name: zk111
Version: 1.0.0
Summary: 测试本地发布模块
Author: zk
Author-email: 2475092874@qq.com
